Metadata-Version: 2.1
Name: jrlib
Version: 2.0.6
Summary: 使用help()函数可查看帮助
Home-page: https://github.com/
Author: Jianrui Li
Author-email: lijianrui7560@qq.com
License: UNKNOWN
Platform: UNKNOWN
Classifier: Programming Language :: Python :: 3
Classifier: License :: OSI Approved :: MIT License
Classifier: Operating System :: OS Independent
